simpot/BNamespace.py
simpot/RdfsClass.py
simpot/__init__.py
simpot/serialize.py
simpot-0.4.0.dist-info/LICENSE.txt
simpot-0.4.0.dist-info/METADATA
simpot-0.4.0.dist-info/WHEEL
simpot-0.4.0.dist-info/top_level.txt
simpot-0.4.0.dist-info/RECORD
