Metadata-Version: 2.1
Name: simpot
Version: 0.4.0
Summary: A simple Python object-triple mapping. ....
Home-page: https://github.com/inovacampus/simpot
Author: Sergio Souza Costa
Author-email: prof.sergio.costa@gmail.com
Classifier: Programming Language :: Python :: 3
Classifier: License :: OSI Approved :: MIT License
Classifier: Operating System :: OS Independent
License-File: LICENSE.txt
Requires-Dist: rdflib
